[{
  "_id": 123,
  "topic": "Space",
  "userName": "SpaceX",
  "userHandle": "@SpaceX",
  "time": "2h",
  "title": "Dennis and Akiko Tito are the first twi crewmembers on Starship's second commercial spaceflight around the Moon",
  "avatar": "spaceximg.jpeg",
  "retweets": "21K",
  "comments": "567",
  "likes": "38.2K",
  "card_image": "random.jpeg"
}, {
    "_id": 345,
    "topic": "Space",
    "userName": "SpaceX",
    "userHandle": "@elonmusk",
    "time": "23h",
    "title": "We might need a different name, as this is basically just starlin with roaming capability, so you can take your terminal anywhere",
    "avatar": "elon_musk.jpeg",
    "retweets": "1.2K",
    "comments": "432",
    "likes": "145.7K",
    "card_image": "random2.jpeg"
  }
]

